karaoke_requests_prep/__init__.py
karaoke_requests_prep/requests_prep.py
karaoke_requests_prep/utils/__init__.py
karaoke_requests_prep/utils/cli.py
karaokenerds_requests_prep-0.3.3.dist-info/LICENSE
karaokenerds_requests_prep-0.3.3.dist-info/METADATA
karaokenerds_requests_prep-0.3.3.dist-info/WHEEL
karaokenerds_requests_prep-0.3.3.dist-info/entry_points.txt
karaokenerds_requests_prep-0.3.3.dist-info/RECORD
