Metadata-Version: 2.1
Name: karaokenerds-requests-prep
Version: 0.3.3
Summary: Prepare for bulk karaoke video creation, by downloading audio and lyrics for top requests on karaokenerds.
Home-page: https://github.com/karaokenerds/karaokenerds-requests-prep
License: MIT
Author: Andrew Beveridge
Author-email: andrew@beveridge.uk
Requires-Python: >=3.9
Classifier: License :: OSI Approved :: MIT License
Classifier: Programming Language :: Python :: 3
Classifier: Programming Language :: Python :: 3.9
Classifier: Programming Language :: Python :: 3.10
Classifier: Programming Language :: Python :: 3.11
Classifier: Programming Language :: Python :: 3.12
Requires-Dist: audio-separator (>=0.8,<0.9)
Requires-Dist: beautifulsoup4 (>=4,<5)
Requires-Dist: fetch-lyrics-from-genius (>=0.1,<0.2)
Requires-Dist: lyricsgenius (>=3,<4)
Requires-Dist: requests (>=2,<3)
Requires-Dist: yt-dlp
Project-URL: Documentation, https://github.com/karaokenerds/karaokenerds-requests-prep/blob/main/README.md
Project-URL: Repository, https://github.com/karaokenerds/karaokenerds-requests-prep
